feagi_connector/PIL_retina.py
feagi_connector/__init__.py
feagi_connector/actuators.py
feagi_connector/configuration.py
feagi_connector/feagi_interface.py
feagi_connector/flag_settings.py
feagi_connector/pns_gateway.py
feagi_connector/retina.py
feagi_connector/router.py
feagi_connector/sensors.py
feagi_connector/testing_mode.py
feagi_connector/trainer.py
feagi_connector/version.py
feagi_connector/sensorimotor/__init__.py
feagi_connector-0.0.40.dist-info/licenses/LICENSE
feagi_connector-0.0.40.dist-info/METADATA
feagi_connector-0.0.40.dist-info/WHEEL
feagi_connector-0.0.40.dist-info/top_level.txt
feagi_connector-0.0.40.dist-info/RECORD
