Metadata-Version: 2.4
Name: feagi_connector
Version: 0.0.40
Summary: Feagi agent to work with general and simulation robots
Home-page: https://github.com/feagi/feagi-connector
Author: Neuraville Inc.
Author-email: feagi@neuraville.com
Project-URL: Bug Tracker, https://github.com/feagi/feagi/issues
Classifier: Programming Language :: Python :: 3 :: Only
Classifier: License :: OSI Approved :: Apache Software License
Classifier: Operating System :: OS Independent
Requires-Python: >=3.6
License-File: LICENSE
Requires-Dist: requests
Requires-Dist: numpy
Requires-Dist: zmq
Requires-Dist: numpy
Requires-Dist: lz4
Requires-Dist: setuptools
Requires-Dist: websockets==12.0
Requires-Dist: opencv-python==4.10.0.84
Requires-Dist: pyserial==3.5
Dynamic: license-file
